{
  "university": "chungang",
  "university_name": "중앙대학교",
  "year": 2020,
  "subject": "engineering_math",
  "subject_name": "공업수학",
  "source_pdf": "중앙_20_공업수학.pdf",
  "question_count": 30,
  "questions": [
    {
      "number": 1,
      "points": "3점",
      "stem": "$\\lim_{\\theta\\to0}\\frac{\\tan\\theta-\\sin\\theta}{\\theta^3}$의 값은?",
      "choices": [
        {
          "label": "①",
          "number": 1,
          "text": "$-\\frac{1}{2}$"
        },
        {
          "label": "②",
          "number": 2,
          "text": "$-\\frac{1}{6}$"
        },
        {
          "label": "③",
          "number": 3,
          "text": "$\\frac{1}{6}$"
        },
        {
          "label": "④",
          "number": 4,
          "text": "$\\frac{1}{2}$"
        }
      ]
    },
    {
      "number": 2,
      "points": "3.5점",
      "stem": "세 점 $(1,0)$, $(1,2)$, $(4,1)$을 꼭짓점으로 하는 삼각형의 둘레와 내부를 $T$라 할 때, $\\iint_Ty^2\\,dx\\,dy$의 값은?",
      "choices": [
        {
          "label": "①",
          "number": 1,
          "text": "$\\frac{3}{2}$"
        },
        {
          "label": "②",
          "number": 2,
          "text": "$\\frac{5}{2}$"
        },
        {
          "label": "③",
          "number": 3,
          "text": "$\\frac{7}{2}$"
        },
        {
          "label": "④",
          "number": 4,
          "text": "$\\frac{9}{2}$"
        }
      ]
    },
    {
      "number": 3,
      "points": "3점",
      "stem": "$2\\times2$ 행렬 $A$가 $A\\begin{pmatrix}1\\\\-1\\end{pmatrix}=\\begin{pmatrix}2\\\\-2\\end{pmatrix}$, $A\\begin{pmatrix}1\\\\1\\end{pmatrix}=\\begin{pmatrix}3\\\\3\\end{pmatrix}$을 만족할 때, $A^{17}\\begin{pmatrix}11\\\\-5\\end{pmatrix}=\\begin{pmatrix}x\\\\y\\end{pmatrix}$라 놓으면 $x-y$의 값은?",
      "choices": [
        {
          "label": "①",
          "number": 1,
          "text": "$2^{19}$"
        },
        {
          "label": "②",
          "number": 2,
          "text": "$2^{21}$"
        },
        {
          "label": "③",
          "number": 3,
          "text": "$3^{19}$"
        },
        {
          "label": "④",
          "number": 4,
          "text": "$3^{21}$"
        }
      ]
    },
    {
      "number": 4,
      "points": "3점",
      "stem": "선형변환 $T:\\mathbb{R}^4\\to\\mathbb{R}^5$를 다음과 같이 정의한다. $T\\mathbf{v}=A\\mathbf{v}$, $A=\\begin{pmatrix}2&0&-2&4\\\\1&0&-2&3\\\\0&4&2&1\\\\6&4&-4&13\\\\2&4&-2&7\\end{pmatrix}$, $\\mathbf{v}\\in\\mathbb{R}^4$. $T$의 계수(rank)를 $r$이라 하고 $T$의 영공간(null space)의 차원을 $n$이라 할 때 $r-n$의 값은?",
      "choices": [
        {
          "label": "①",
          "number": 1,
          "text": "$0$"
        },
        {
          "label": "②",
          "number": 2,
          "text": "$1$"
        },
        {
          "label": "③",
          "number": 3,
          "text": "$2$"
        },
        {
          "label": "④",
          "number": 4,
          "text": "$3$"
        }
      ]
    },
    {
      "number": 5,
      "points": "4점",
      "stem": "곡면 $S=\\{(x,y,z)\\in\\mathbb{R}^3:z=\\frac{1}{2}y^2,\\ 0\\leq x\\leq1,\\ 0\\leq y\\leq1\\}$에 대하여 곡면적분 $\\iint_S\\sqrt{1+y^2}\\,dS$의 값은?",
      "choices": [
        {
          "label": "①",
          "number": 1,
          "text": "$\\frac{1}{3}$"
        },
        {
          "label": "②",
          "number": 2,
          "text": "$\\frac{2}{3}$"
        },
        {
          "label": "③",
          "number": 3,
          "text": "$1$"
        },
        {
          "label": "④",
          "number": 4,
          "text": "$\\frac{4}{3}$"
        }
      ]
    },
    {
      "number": 6,
      "points": "3점",
      "stem": "$\\int_0^1\\sqrt{\\frac{1-x}{1+x}}\\,dx$의 값은?",
      "choices": [
        {
          "label": "①",
          "number": 1,
          "text": "$-1-\\frac{\\pi}{2}$"
        },
        {
          "label": "②",
          "number": 2,
          "text": "$-1+\\frac{\\pi}{2}$"
        },
        {
          "label": "③",
          "number": 3,
          "text": "$1-\\frac{\\pi}{2}$"
        },
        {
          "label": "④",
          "number": 4,
          "text": "$1+\\frac{\\pi}{2}$"
        }
      ]
    },
    {
      "number": 7,
      "points": "4점",
      "stem": "$t>0$일 때, 함수 $A(t)=\\frac{1}{2}\\cosh t\\sinh t-\\int_1^{\\cosh t}\\sqrt{\\theta^2-1}\\,d\\theta$의 도함수 $A'(t)$를 구하면?",
      "choices": [
        {
          "label": "①",
          "number": 1,
          "text": "$A'(t)=\\frac{1}{2}+\\sinh^2t$"
        },
        {
          "label": "②",
          "number": 2,
          "text": "$A'(t)=\\frac{1}{2}+\\sinh^2t-\\sinh t$"
        },
        {
          "label": "③",
          "number": 3,
          "text": "$A'(t)=\\frac{1}{2}$"
        },
        {
          "label": "④",
          "number": 4,
          "text": "$A'(t)=\\frac{1}{2}+\\sinh^2t+\\sinh t$"
        }
      ]
    },
    {
      "number": 8,
      "points": "4점",
      "stem": "$\\mathbf{r}(t)=\\frac{1}{\\sqrt{t}}(\\cos t,\\sin t,t)$일 때, 외적 $\\mathbf{r}(t)\\times\\mathbf{r}'(t)$의 크기(norm)를 구하면? (단, $t>0$)",
      "choices": [
        {
          "label": "①",
          "number": 1,
          "text": "$\\sqrt{1+\\frac{2}{t^2}}$"
        },
        {
          "label": "②",
          "number": 2,
          "text": "$\\sqrt{t+\\frac{1}{t}}$"
        },
        {
          "label": "③",
          "number": 3,
          "text": "$\\frac{1}{2}\\sqrt{\\frac{5}{t}+\\frac{1}{t^3}}$"
        },
        {
          "label": "④",
          "number": 4,
          "text": "$\\sqrt{1+\\frac{1+\\sin2t}{t}}$"
        }
      ]
    },
    {
      "number": 9,
      "points": "3점",
      "stem": "함수 $B(x)=\\begin{cases}\\frac{x}{e^x-1},&x\\neq0\\\\1,&x=0\\end{cases}$의 미분계수 $B'(0)$의 값은?",
      "choices": [
        {
          "label": "①",
          "number": 1,
          "text": "$-\\frac{1}{2}$"
        },
        {
          "label": "②",
          "number": 2,
          "text": "$-\\frac{1}{6}$"
        },
        {
          "label": "③",
          "number": 3,
          "text": "$\\frac{1}{6}$"
        },
        {
          "label": "④",
          "number": 4,
          "text": "$\\frac{1}{2}$"
        }
      ]
    },
    {
      "number": 10,
      "points": "3점",
      "stem": "구 $x^2+y^2+z^2=19$ 위에서 함수 $f(x,y,z)=2x+3y+5z$의 최댓값은?",
      "choices": [
        {
          "label": "①",
          "number": 1,
          "text": "$19\\sqrt{3}$"
        },
        {
          "label": "②",
          "number": 2,
          "text": "$19\\sqrt{2}$"
        },
        {
          "label": "③",
          "number": 3,
          "text": "$38\\sqrt{3}$"
        },
        {
          "label": "④",
          "number": 4,
          "text": "$38\\sqrt{2}$"
        }
      ]
    },
    {
      "number": 11,
      "points": "3.5점",
      "stem": "$y=y(x)$가 미분방정식 $y'=(x+1)e^{-x}y^2$, $y(0)=1$의 해일 때, $y(-1)$의 값은?",
      "choices": [
        {
          "label": "①",
          "number": 1,
          "text": "$\\frac{1}{e+1}$"
        },
        {
          "label": "②",
          "number": 2,
          "text": "$\\frac{1}{e-1}$"
        },
        {
          "label": "③",
          "number": 3,
          "text": "$\\frac{-1}{e+1}$"
        },
        {
          "label": "④",
          "number": 4,
          "text": "$\\frac{-1}{e-1}$"
        }
      ]
    },
    {
      "number": 12,
      "points": "3.5점",
      "stem": "$x=x(t)$가 미분방정식 $x'=x\\sin t+2te^{-\\cos t}$, $x(0)=1$의 해일 때, $x\\left(\\frac{\\pi}{2}\\right)$의 값은?",
      "choices": [
        {
          "label": "①",
          "number": 1,
          "text": "$\\frac{\\pi^2}{4}+e$"
        },
        {
          "label": "②",
          "number": 2,
          "text": "$\\frac{\\pi^2}{4}-e$"
        },
        {
          "label": "③",
          "number": 3,
          "text": "$-\\frac{\\pi^2}{4}+e$"
        },
        {
          "label": "④",
          "number": 4,
          "text": "$-\\frac{\\pi^2}{4}-e$"
        }
      ]
    },
    {
      "number": 13,
      "points": "3.5점",
      "stem": "다음 중에서 미분방정식 $y(y'-1)=xy'$, $y(0)=2$의 해는?",
      "choices": [
        {
          "label": "①",
          "number": 1,
          "text": "$xy+\\frac{y^2}{4}=1$"
        },
        {
          "label": "②",
          "number": 2,
          "text": "$xy+\\frac{y^2}{2}=2$"
        },
        {
          "label": "③",
          "number": 3,
          "text": "$xy-\\frac{y^2}{2}=-2$"
        },
        {
          "label": "④",
          "number": 4,
          "text": "$xy-\\frac{y^2}{4}=-1$"
        }
      ]
    },
    {
      "number": 14,
      "points": "3점",
      "stem": "다음 $2$개의 집합 $\\Phi_1$, $\\Phi_2$에 대한 선형 독립, 선형 종속 여부를 바르게 나타낸 것은? $\\Phi_1=\\{y_1(x)=\\log_2x,\\ y_2(x)=\\log_5x,\\ y_3(x)=\\log_{10}x\\}$, $\\Phi_2=\\{y_1(x)=\\cosh x,\\ y_2(x)=\\sinh x,\\ y_3(x)=e^x\\}$",
      "choices": [
        {
          "label": "①",
          "number": 1,
          "text": "$\\Phi_1$: 선형 독립, $\\Phi_2$: 선형 독립"
        },
        {
          "label": "②",
          "number": 2,
          "text": "$\\Phi_1$: 선형 독립, $\\Phi_2$: 선형 종속"
        },
        {
          "label": "③",
          "number": 3,
          "text": "$\\Phi_1$: 선형 종속, $\\Phi_2$: 선형 독립"
        },
        {
          "label": "④",
          "number": 4,
          "text": "$\\Phi_1$: 선형 종속, $\\Phi_2$: 선형 종속"
        }
      ]
    },
    {
      "number": 15,
      "points": "3.5점",
      "stem": "$y=y(x)$가 미분방정식 $y'+y=5e^x\\cos x$, $y(0)=2$의 해일 때, $y\\left(-\\frac{\\pi}{2}\\right)$의 값은?",
      "choices": [
        {
          "label": "①",
          "number": 1,
          "text": "$e^{\\frac{\\pi}{2}}$"
        },
        {
          "label": "②",
          "number": 2,
          "text": "$-e^{\\frac{\\pi}{2}}$"
        },
        {
          "label": "③",
          "number": 3,
          "text": "$e^{-\\frac{\\pi}{2}}$"
        },
        {
          "label": "④",
          "number": 4,
          "text": "$-e^{-\\frac{\\pi}{2}}$"
        }
      ]
    },
    {
      "number": 16,
      "points": "3점",
      "stem": "$x>0$일 때, 미분방정식 $x^3y'''-6y=0$의 일반해를 구하면 $y=c_1x^a+[c_2\\cos(b\\ln x)+c_3\\sin(c\\ln x)]$이다. 이때, $a+bc$의 값은?",
      "choices": [
        {
          "label": "①",
          "number": 1,
          "text": "$3$"
        },
        {
          "label": "②",
          "number": 2,
          "text": "$5$"
        },
        {
          "label": "③",
          "number": 3,
          "text": "$7$"
        },
        {
          "label": "④",
          "number": 4,
          "text": "$9$"
        }
      ]
    },
    {
      "number": 17,
      "points": "3.5점",
      "stem": "연립미분방정식 $x'(t)=y(t)+e^{2t}$, $y'(t)=x(t)-3e^{2t}$, $x(0)=-\\frac{7}{3}$, $y(0)=-\\frac{5}{3}$를 만족하는 $x(t)$, $y(t)$에 대하여 $x(1)+y(1)$의 값은?",
      "choices": [
        {
          "label": "①",
          "number": 1,
          "text": "$2e+2e^2$"
        },
        {
          "label": "②",
          "number": 2,
          "text": "$2e-2e^2$"
        },
        {
          "label": "③",
          "number": 3,
          "text": "$-2e+2e^2$"
        },
        {
          "label": "④",
          "number": 4,
          "text": "$-2e-2e^2$"
        }
      ]
    },
    {
      "number": 18,
      "points": "3.5점",
      "stem": "$G(s)=\\frac{e^{-2s}}{s^2(s-1)}$의 라플라스 역변환을 $g(t)$라 할 때, $g(2)$의 값은?",
      "choices": [
        {
          "label": "①",
          "number": 1,
          "text": "$-1$"
        },
        {
          "label": "②",
          "number": 2,
          "text": "$0$"
        },
        {
          "label": "③",
          "number": 3,
          "text": "$1$"
        },
        {
          "label": "④",
          "number": 4,
          "text": "$2$"
        }
      ]
    },
    {
      "number": 19,
      "points": "3.5점",
      "stem": "함수 $g(t)=t\\cos(2t)$에 대한 라플라스 변환이 $G(s)$로 주어질 때, $G(1)$의 값은?",
      "choices": [
        {
          "label": "①",
          "number": 1,
          "text": "$-\\frac{3}{25}$"
        },
        {
          "label": "②",
          "number": 2,
          "text": "$-\\frac{2}{25}$"
        },
        {
          "label": "③",
          "number": 3,
          "text": "$\\frac{2}{25}$"
        },
        {
          "label": "④",
          "number": 4,
          "text": "$\\frac{3}{25}$"
        }
      ]
    },
    {
      "number": 20,
      "points": "3점",
      "stem": "$y=y(t)$가 미적분 방정식 $\\frac{dy}{dt}+6y(t)+9\\int_0^t y(\\tau)\\,d\\tau=1$, $y(0)=0$의 해일 때, $y(1)$의 값은?",
      "choices": [
        {
          "label": "①",
          "number": 1,
          "text": "$\\frac{1}{4}e^{-3}$"
        },
        {
          "label": "②",
          "number": 2,
          "text": "$\\frac{1}{2}e^{-3}$"
        },
        {
          "label": "③",
          "number": 3,
          "text": "$e^{-3}$"
        },
        {
          "label": "④",
          "number": 4,
          "text": "$2e^{-3}$"
        }
      ]
    },
    {
      "number": 21,
      "points": "3점",
      "stem": "함수 $g(t)=\\begin{cases}1,&0\\leq t<1\\\\0,&1\\leq t<2\\\\1,&t\\geq2\\end{cases}$에 대한 라플라스 변환이 $G(s)=\\frac{A}{s}+B\\frac{e^{-s}}{s}+C\\frac{e^{-Ds}}{s}$로 주어질 때, 상수 $A$, $B$, $C$, $D$의 곱은?",
      "choices": [
        {
          "label": "①",
          "number": 1,
          "text": "$2$"
        },
        {
          "label": "②",
          "number": 2,
          "text": "$4$"
        },
        {
          "label": "③",
          "number": 3,
          "text": "$-2$"
        },
        {
          "label": "④",
          "number": 4,
          "text": "$-4$"
        }
      ]
    },
    {
      "number": 22,
      "points": "2.5점",
      "stem": "주기가 $1$인 함수 $f(x)$를 다음과 같이 정의하자. $f(x)=\\begin{cases}0,&-\\frac{1}{2}<x\\leq0\\\\1,&0<x<\\frac{1}{4}\\\\0,&\\frac{1}{4}\\leq x<\\frac{1}{2}\\end{cases}$. $f(x)$를 복소 Fourier 급수 $f(x)=\\sum_{n=-\\infty}^{\\infty}c_ne^{i2\\pi nx}$로 나타낼 때, $c_n$을 구하면? (단, $n\\neq0$)",
      "choices": [
        {
          "label": "①",
          "number": 1,
          "text": "$\\frac{i}{2\\pi n}\\left[(-i)^n-1\\right]$"
        },
        {
          "label": "②",
          "number": 2,
          "text": "$\\frac{i}{2\\pi n}\\left[-i^n+1\\right]$"
        },
        {
          "label": "③",
          "number": 3,
          "text": "$\\frac{i}{2\\pi n}\\left[i^n+1\\right]$"
        },
        {
          "label": "④",
          "number": 4,
          "text": "$\\frac{i}{2\\pi n}\\left[(-i)^n+1\\right]$"
        }
      ]
    },
    {
      "number": 23,
      "points": "3점",
      "stem": "$x>0$에서 다음 Fourier 적분이 성립하는 $A(\\alpha)$와 $B(\\alpha)$가 올바르게 짝지어진 것은? $e^{-x}\\cos x=\\frac{1}{\\pi}\\int_0^{\\infty}[A(\\alpha)\\cos\\alpha x+B(\\alpha)\\sin\\alpha x]\\,d\\alpha$",
      "choices": [
        {
          "label": "①",
          "number": 1,
          "text": "$A(\\alpha)=\\frac{\\alpha^2+2}{\\alpha^4+4},\\ B(\\alpha)=\\frac{\\alpha^3}{\\alpha^4+4}$"
        },
        {
          "label": "②",
          "number": 2,
          "text": "$A(\\alpha)=\\frac{\\alpha^2-2}{\\alpha^4+4},\\ B(\\alpha)=\\frac{\\alpha^3}{\\alpha^4+4}$"
        },
        {
          "label": "③",
          "number": 3,
          "text": "$A(\\alpha)=\\frac{\\alpha^2-2}{\\alpha^4+4},\\ B(\\alpha)=\\frac{2\\alpha^3}{\\alpha^4+4}$"
        },
        {
          "label": "④",
          "number": 4,
          "text": "$A(\\alpha)=\\frac{\\alpha^2+2}{\\alpha^4+4},\\ B(\\alpha)=\\frac{2\\alpha^3}{\\alpha^4+4}$"
        }
      ]
    },
    {
      "number": 24,
      "points": "3.5점",
      "stem": "다음 <보기> 중 Taylor 급수와 수렴영역이 올바르게 짝지어진 것은 모두 몇 개인가?",
      "statement_box": [
        {
          "label": "(가)",
          "text": "$\\frac{1}{z}=\\sum_{k=0}^{\\infty}(-1)^k\\frac{(z-1-i)^k}{(1+i)^{k+1}}$, $|z-(1+i)|<\\sqrt{2}$"
        },
        {
          "label": "(나)",
          "text": "$\\frac{1}{3-z}=\\sum_{k=0}^{\\infty}\\frac{(z-2i)^k}{(3-2i)^{k+1}}$, $|z-2i|<\\sqrt{13}$"
        },
        {
          "label": "(다)",
          "text": "$\\frac{1+z}{1-z}=-1+2\\sum_{k=1}^{\\infty}\\frac{(z-i)^k}{(1-i)^{k+1}}$, $|z-i|<\\sqrt{2}$"
        },
        {
          "label": "(라)",
          "text": "$\\frac{z}{1-z-z^2}=\\frac{1}{\\sqrt{5}}\\sum_{k=1}^{\\infty}\\left[\\left(\\frac{2}{\\sqrt{5}-1}\\right)^k-\\left(-\\frac{2}{\\sqrt{5}+1}\\right)^k\\right]z^k$, $|z|<\\frac{\\sqrt{5}-1}{2}$"
        }
      ],
      "choices": [
        {
          "label": "①",
          "number": 1,
          "text": "$1$개"
        },
        {
          "label": "②",
          "number": 2,
          "text": "$2$개"
        },
        {
          "label": "③",
          "number": 3,
          "text": "$3$개"
        },
        {
          "label": "④",
          "number": 4,
          "text": "$4$개"
        }
      ]
    },
    {
      "number": 25,
      "points": "3점",
      "stem": "$\\cos^{-1}(2i)$를 나타내는 값이 아닌 것은?",
      "choices": [
        {
          "label": "①",
          "number": 1,
          "text": "$\\frac{5\\pi}{2}-i\\log_e(\\sqrt{5}+2)$"
        },
        {
          "label": "②",
          "number": 2,
          "text": "$\\frac{7\\pi}{2}+i\\log_e(\\sqrt{5}-2)$"
        },
        {
          "label": "③",
          "number": 3,
          "text": "$\\frac{3\\pi}{2}-i\\log_e(\\sqrt{5}-2)$"
        },
        {
          "label": "④",
          "number": 4,
          "text": "$\\frac{11\\pi}{2}+i\\log_e(\\sqrt{5}+2)$"
        }
      ]
    },
    {
      "number": 26,
      "points": "4점",
      "stem": "다음 <보기> 중 옳은 것은 모두 몇 개인가? (단, $z=x+iy$이다.)",
      "statement_box": [
        {
          "label": "(가)",
          "text": "주치(principal value) 로그에서 $(1+i)^{(2+i)}$의 실수부는 $e^{(\\log_e2-\\frac{\\pi}{4})}\\cos\\left(\\log_e\\sqrt{2}+\\frac{\\pi}{2}\\right)$이다."
        },
        {
          "label": "(나)",
          "text": "모든 $z$에 대하여 $\\sin\\bar z=\\overline{\\sin z}$는 항상 성립한다. (단, $\\bar z$와 $\\overline{\\sin z}$는 $z$와 $\\sin z$의 켤레복소수이다.)"
        },
        {
          "label": "(다)",
          "text": "복소함수 $f(z)=\\sin x\\cosh y+i\\cos x\\sinh y$는 모든 $z$에 대하여 해석적인 완전함수이다."
        },
        {
          "label": "(라)",
          "text": "복소함수 $g(z)=\\frac{\\cos z-\\cos2z}{z^6}$는 $z=0$에서 차수가 $4$인 극(pole)을 가진다."
        },
        {
          "label": "(마)",
          "text": "복소사상 $w=\\frac{1}{z}$에 의한 $\\{|z|^2\\leq2\\operatorname{Im}(z)\\}$ (단, $z\\neq0$)의 상(image)은 $\\{\\operatorname{Im}(w)\\leq-\\frac{1}{2}\\}$이다."
        }
      ],
      "choices": [
        {
          "label": "①",
          "number": 1,
          "text": "$2$개"
        },
        {
          "label": "②",
          "number": 2,
          "text": "$3$개"
        },
        {
          "label": "③",
          "number": 3,
          "text": "$4$개"
        },
        {
          "label": "④",
          "number": 4,
          "text": "$5$개"
        }
      ]
    },
    {
      "number": 27,
      "points": "3점",
      "stem": "복소함수 $f(z)=e^z\\cos z$를 Maclaurin 급수 $f(z)=1+\\sum_{k=1}^{\\infty}a_kz^k$로 전개하였을 때 $\\frac{a_{20}}{a_{21}}$의 값은?",
      "choices": [
        {
          "label": "①",
          "number": 1,
          "text": "$-21\\sqrt{2}$"
        },
        {
          "label": "②",
          "number": 2,
          "text": "$-21$"
        },
        {
          "label": "③",
          "number": 3,
          "text": "$21$"
        },
        {
          "label": "④",
          "number": 4,
          "text": "$21\\sqrt{2}$"
        }
      ]
    },
    {
      "number": 28,
      "points": "3.5점",
      "stem": "$C$를 원 $|z|=\\frac{3}{4}$이라 할 때, $\\int_C\\left(\\frac{\\cos z}{z^3-z^2}+\\frac{e^{i\\pi z}}{2z^2-5z+2}\\right)dz$를 계산하면? (단, $C$의 방향은 시계반대방향이다.)",
      "choices": [
        {
          "label": "①",
          "number": 1,
          "text": "$2\\pi\\left(\\frac{2}{3}+i\\right)$"
        },
        {
          "label": "②",
          "number": 2,
          "text": "$2\\pi\\left(\\frac{1}{3}+i\\right)$"
        },
        {
          "label": "③",
          "number": 3,
          "text": "$2\\pi\\left(\\frac{2}{3}-i\\right)$"
        },
        {
          "label": "④",
          "number": 4,
          "text": "$2\\pi\\left(\\frac{1}{3}-i\\right)$"
        }
      ]
    },
    {
      "number": 29,
      "points": "4점",
      "stem": "$\\int_0^{2\\pi}\\frac{\\cos^2 3\\theta}{5-4\\cos2\\theta}\\,d\\theta$의 값은?",
      "choices": [
        {
          "label": "①",
          "number": 1,
          "text": "$\\frac{3\\pi}{4}$"
        },
        {
          "label": "②",
          "number": 2,
          "text": "$\\frac{3\\pi}{8}$"
        },
        {
          "label": "③",
          "number": 3,
          "text": "$\\frac{3\\pi}{16}$"
        },
        {
          "label": "④",
          "number": 4,
          "text": "$\\frac{3\\pi}{32}$"
        }
      ]
    },
    {
      "number": 30,
      "points": "3.5점",
      "stem": "$\\int_{-\\infty}^{\\infty}\\frac{x^2}{1+x^4}\\,dx$의 값은?",
      "choices": [
        {
          "label": "①",
          "number": 1,
          "text": "$\\frac{\\sqrt{2}\\pi}{8}$"
        },
        {
          "label": "②",
          "number": 2,
          "text": "$\\frac{\\sqrt{2}\\pi}{4}$"
        },
        {
          "label": "③",
          "number": 3,
          "text": "$\\frac{\\sqrt{2}\\pi}{2}$"
        },
        {
          "label": "④",
          "number": 4,
          "text": "$\\sqrt{2}\\pi$"
        }
      ]
    }
  ]
}
